<?xml version="1.0" encoding="utf-8"?>
<!DOCTYPE hibernate-mapping PUBLIC "-//Hibernate/Hibernate Mapping DTD 3.0//EN"
"http://hibernate.sourceforge.net/hibernate-mapping-3.0.dtd">
<!-- 
    Mapping file autogenerated by MyEclipse Persistence Tools
-->
<hibernate-mapping>
    <class name="com.rongji.websiteMonitor.persistence.Monitortype" table="MONITORTYPE" >
       <comment>监测类型ID</comment>
        <id name="mtId" type="java.lang.String">
            <column name="Mt_ID" length="8" />
            <generator class="assigned" />
        </id>
        <property name="mtName" type="java.lang.String">
            <column name="Mt_NAME" length="100">
                <comment>监测类型名</comment>
            </column>
        </property>
         <property name="mtAlias" type="java.lang.String">
            <column name="Mt_ALIAS" length="100">
                <comment>监测类型别名</comment>
            </column>
        </property>
    </class>
</hibernate-mapping>
